{
  "users": [
    {
      "email": "cu@cu",
      "password": "$2a$10$RjaljzqCTPlev99ZFoOrX.5cg2R2JuWdNdqIDiF8MXYowb0DQ9qJa",
      "name": "cucu",
      "likedSongIds": [
        2
      ],
      "roles": [],
      "id": 1
    }
  ],
  "songs": [
    {
      "id": 1,
      "userId": 1,
      "indexInAlbum": 1,
      "name": "songname",
      "albumId": 1,
      "likes": 90,
      "artistIds": [
        1,
        2
      ],
      "genres": [
        "Test",
        "Asdf",
        "Adfasdfkjasödj öasljö"
      ],
      "length": 197,
      "lyrics": [
        {
          "id": 1,
          "groupName": "Verse",
          "content": [
            {
              "id": 1,
              "timestamp": 1,
              "text": "Test line one"
            },
            {
              "id": 2,
              "timestamp": 3,
              "text": "Test line two"
            }
          ]
        },
        {
          "id": 2,
          "groupName": "Chorus",
          "content": [
            {
              "id": 1,
              "timestamp": 10,
              "text": "Test line one"
            },
            {
              "id": 2,
              "timestamp": 15,
              "text": "Test line two"
            }
          ]
        }
      ],
      "lastEdit": "0"
    },
    {
      "id": 2,
      "userId": 1,
      "indexInAlbum": 2,
      "name": "songname",
      "albumId": 1,
      "likes": 90,
      "artistIds": [
        1,
        2
      ],
      "genres": [
        "Test",
        "Asdf",
        "Adfasdfkjasödj öasljö"
      ],
      "length": 197,
      "lyrics": [
        {
          "id": 1,
          "groupName": "Verse",
          "content": [
            {
              "id": 1,
              "timestamp": 1,
              "text": "Test line one"
            },
            {
              "id": 2,
              "timestamp": 3,
              "text": "Test line two"
            }
          ]
        },
        {
          "id": 2,
          "groupName": "Chorus",
          "content": [
            {
              "id": 1,
              "timestamp": 10,
              "text": "Test line one"
            },
            {
              "id": 2,
              "timestamp": 15,
              "text": "Test line two"
            }
          ]
        }
      ],
      "lastEdit": "0"
    }
  ],
  "albums": [
    {
      "id": 1,
      "userId": 1,
      "name": "aasdfasfdasdfa asa asdf ",
      "year": 2005,
      "artistIds": [
        1
      ],
      "coverImage": "d077db5e-c482-487e-ac8c-bc5c4eabdf5b.png",
      "last-edit": "0"
    },
    {
      "id": 2,
      "userId": 1,
      "name": "Albumname 2",
      "year": 2050,
      "artistIds": [
        2
      ],
      "coverImage": "d077db5e-c482-487e-ac8c-bc5c4eabdf5b.png",
      "last-edit": "0"
    }
  ],
  "artists": [
    {
      "name": "adsfasdfasdf",
      "lastEdit": "2022-04-22T13:54:22.424Z",
      "filePath": "/artistimages/bccf5a52-5cc7-4f1a-a836-3bf66f6ad22e.jpeg",
      "userId": 1,
      "id": 1
    },
    {
      "name": "adsf",
      "lastEdit": "2022-04-22T13:59:00.063Z",
      "filePath": "/artistimages/4053e62e-897f-4040-bb7d-37a15b4b7d0a.jpeg",
      "userId": 1,
      "id": 4
    },
    {
      "name": "asdf",
      "lastEdit": "2022-04-22T13:59:12.276Z",
      "filePath": "/artistimages/a0c2a950-6613-4936-a764-06cfe61cb18a.png",
      "userId": 1,
      "id": 5
    },
    {
      "name": "test ",
      "filePath": "/artistimages/da84791a-aa42-47e1-b20c-aa830e490fa3.png",
      "lastEdit": "2022-04-25T08:57:37.360Z",
      "userId": 1,
      "id": 6
    },
    {
      "name": "fsdfsdfsdfasdffffffff",
      "filePath": "/artistimages/6793c4ec-c29b-4a19-a045-a93ed518e942.png",
      "lastEdit": "2022-04-25T08:59:26.151Z",
      "userId": 1,
      "id": 7
    },
    {
      "name": "sdfg",
      "filePath": "/artistimages/7955326c-a082-4e50-abea-c17391754b6d.jpeg",
      "lastEdit": "2022-04-25T09:03:32.065Z",
      "userId": 1,
      "id": 8
    },
    {
      "name": "a",
      "filePath": "/artistimages/9dd87c67-77cf-4370-9364-519dceaa59d0.png",
      "lastEdit": "2022-04-25T09:04:19.745Z",
      "userId": 1,
      "id": 9
    }
  ]
}